README.md
setup.py
Mapa/Mapa.py
Mapa/__init__.py
libgranzottiPyTools/__init__.py
libgranzottiPyTools/github_api.py
libgranzottiPyTools.egg-info/PKG-INFO
libgranzottiPyTools.egg-info/SOURCES.txt
libgranzottiPyTools.egg-info/dependency_links.txt
libgranzottiPyTools.egg-info/not-zip-safe
libgranzottiPyTools.egg-info/requires.txt
libgranzottiPyTools.egg-info/top_level.txt