Metadata-Version: 2.1
Name: libgranzottiPyTools
Version: 0.2
Summary: Para aprender a usar o pytools
Home-page: https://github.com/GiovanniGranzotti/granzottiPyTools
Author: Giovanni Granzotti
Author-email: giogranzotti@hotmail.com
License: GNU AFFERO GENERAL PUBLIC LICENSE
Platform: UNKNOWN
Classifier: Development Status :: 2 - Pre-Alpha
Classifier: Environment :: Console
Classifier: Intended Audience :: Developers
Classifier: License :: OSI Approved :: GNU Affero General Public License v3 or later (AGPLv3+)
Classifier: Operating System :: OS Independent
Classifier: Programming Language :: Python
Classifier: Programming Language :: Python :: 3.8
Classifier: Framework :: Pytest
